{
  "id": "adult-care-47",
  "category": "parents",
  "topic": "doctorsHospitals",
  "subtopicId": "medicos-y-visitas-al-hospital",
  "es": {
    "title": "Cuando su hijo ya es demasiado mayor para seguir yendo al pediatra",
    "description": "Parece que fue ayer cuando llegó al consultorio del pediatra en la primera visita médica de su hijo. Pero llegará un momento en que su hijo necesitará recibir una atención médica propia de los adultos. Este cambio le puede imponer, tanto a usted como a su hijo. Pero si ambos están preparados, podrán entrar con suavidad en el camino de su hijo hacia la vida adulta. Ayudar a su hijo en edad adolescente a encontrar un nuevo médico Cuando un niño se convierte en adulto, podrá pasar a visitarse con un médico de atención primaria para adultos, sea un médico de medicina interna (internista), un médico de cabecera o un médico de medicina familiar. Los pediatras están formados para cuidar desde a bebés hasta a adultos jóvenes. No todos los pediatras siguen la misma política en los que respecta a los límites de edad, o sea que pida información a su pediatra cuando su hijo entre en la adolescencia. Pida al pediatra de su hijo que le recomiende a otro profesional si no dispone de un médico de familia que pueda atender a su hijo o, si su hijo tiene una afección crónica, requerirá la atención de un especialista médico para adultos. Si su hijo tiene una afección rara, una discapacidad o una afección pediátrica (que solo se desarrolla en la infancia), puede ser todo un reto encontrar a un buen médico de atención primaria o a un especialista para adultos. Usted querrá contar con alguien que se sienta cómodo cuidando de las complejas necesidades de su hijo. Por lo tanto, empiece a buscar médicos con tiempo de antelación, durante la adolescencia de su hijo. Pregunte si es posible que su hijo consulte a un médico nuevo durante un período de prueba. Después, haga un seguimiento con el especialista pediátrico para hablar sobre cómo van las cosas. Resérvese abundante tiempo para completar este proceso. Así, si surgiera algún problema, su hijo se podría seguir yendo a su especialista pediátrico hasta encontrar a otro profesional médico para adultos que encajara en lo que buscan. Ayudar a su hijo en edad adolescente a elegir una cobertura médica En Estados Unidos, si su hijo depende de su cobertura médica, el Acta de Cobertura Accesible (ACA, por sus siglas en inglés) permite cubrir a su hijo hasta los 26 años de edad. No importa si su hijo está yendo a la universidad, vive con usted, trabaja o está casado. Su hijo puede seguir estando cubierto por su póliza médica. Si su hijo depende de su póliza de salud laboral, su cobertura concluirá el día en que cumpla 26 años. Por lo tanto, empiecen a buscar una nueva cobertura con bastante tiempo de antelación a esa fecha. Si su hijo está cubierto con un plan ACA de Mercado de Seguro Médico, estará cubierto hasta el 31 de diciembre del año en el que cumpla 26 años. ¿Cuáles son las opciones disponibles? Muchas empresas ofrecen una cobertura de salud grupal como parte del paquete de prestaciones para sus empleados. Esto permite a los empresarios personalizar un plan que puede incluir el cuidado dental, el cuidado de la vista, la atención de emergencia y los cuidados médicos ordinarios. El seguro por discapacidad a largo plazo ofrece prestaciones médicas para quienes estén sin trabajo durante un largo período de tiempo. Si se lo ofrecen, tendrá un coste añadido. Si está asegurado a través de una empresa, su hijo pagará lo siguiente: • un costo mensual (prima) • cualquier copago y gastos de bolsillo para visitar a los profesionales de la salud, sean médicos o farmacéuticos ¿Y si su hijo adulto deja de estar cubierto por su póliza médica y ni su empresario ni su pareja le ofrecen una cobertura médica? En tal caso, podría ser elegible para recibir la cobertura COBRA, la ley Ómnibus Consolidada de Reconciliación Presupuestaria. En Estados Unidos, las leyes obligan a todas las compañías aseguradoras a extender temporalmente hasta un máximo de 36 meses la cobertura de un plan grupal a quienes antes estaban cubiertos por él. La cobertura COBRA no entra en vigor automáticamente. Su hijo debe solicitar la cobertura y debe hacerlo pronto, puesto que el período de elegibilidad es limitado. Las primas serán más elevadas que las que su hijo pagaba cuando dependía de su plan. Su hijo también puede optar por una cobertura de salud individual a través del seguro Marketplace de la página HealthCare.gov. La mayoría de los planes se basan en los ingresos de su hijo cuando sea adulto. Muchos están subsidiados para que sean más asequibles. Consideraciones especiales Las compañías médicas no pueden rechazar a personas con enfermedades preexistentes o cobrarles más por su cobertura. Si su hijo tiene necesidades médicas especiales, es posible que su póliza disponga de una cláusula para un adulto discapacitado. Esta cláusula permite que adultos con discapacidades desde la infancia permanezcan dentro de la póliza de sus padres de forma indefinida. Infórmese para saber si su aseguradora ofrece esta posibilidad. Los adultos que estén discapacitados pueden recibir una cobertura médica a través del programa gubernamental Medicaid si sus ingresos no les permiten cubrir el costo de los servicios médicos o si califican para recibir el Ingreso de Seguridad Complementario (SSI, por sus siglas en inglés) o lo están recibiendo. Aquellas personas a quienes se les haya reconocido la discapacidad antes de cumplir los 22 años de edad también pueden ser elegibles para recibir el Seguro de Discapacidad de la Seguridad Social (SSDI, por sus siglas en inglés). Estas prestaciones se ofrecen a niños discapacitados cuyos padres pagaron a la Seguridad Social a lo largo de sus carreras profesionales. Los niños cuyos padres fallecieron, se jubilaron o se reconocieron como discapacitados pueden calificar para recibir prestaciones. Después de recibir el SSDI durante 24 meses, también son elegibles para beneficiarse del de seguro Medicare del gobierno de Estados Unidos. Ayudar a su hijo en edad adolescente a ser un paciente responsable La atención médica de un adulto se basa en la responsabilidad del paciente. Esta responsabilidad viene acompañada de un control sobre tu salud. Por lo tanto, su hijo tomará todas las decisiones médicas y tiene derecho a la privacidad en lo que respecta a todas sus afecciones médicas. Usted no obtendrá esa información a menos que su hijo decida compartirla con usted. Es importante que los adultos jóvenes compartan su información médica con todos los profesionales médicos que los atiendan. Esto incluye las enfermedades que hayan tenido, las operaciones a que se hayan sometido, los medicamentos que tomen y las vacunas que se hayan puesto. También deberían compartir con sus médicos cualquier reacción alérgica a medicamentos y cualquier antecedente familiar de enfermedades, como el cáncer o las enfermedades cardíacas. Anime a su hijo a conservar copias de todos sus informes médicos así como un listado actualizado de los medicamentos que toma. Y, aunque es importante consultar a un médico ante cualquier problema o preocupación relacionada con la salud, también lo es acudir a todos las visitas de control regulares y hacerse pruebas de cribado de tipo preventivo. Las pruebas de cribado preventivo se basan en los antecedentes médicos personales y familiares de su hijo. ¿Cómo puedo ayudar a mi hijo a hacerse cargo de su salud? Ayude a su hijo a co-gestionar sus cuidados médicos durante la adolescencia. Poco a poco, vaya animándolo a adquirir un rol cada vez más activo. Por ejemplo, él puede programar sus citas y pasar a recoger sus medicamentos por la farmacia. Esto le permitirá ganar confianza y le mostrará a usted que es capaz de cuidar de sí mismo. El cambio a la atención médica propia de los adultos no ocurrirá de la noche a la mañana. Pero planificar las cosas con tiempo y hablar sobre qué espera de él ayudará a su hijo a gestionar sus cuidados médicos cuando llegue el momento."
  },
  "en": {
    "title": "When Your Child Outgrows Pediatric Care",
    "description": "It might seem like only yesterday that you stepped into the pediatrician's office for your child's very first visit. But the time will come when your child needs to move into adult health care. This change can seem overwhelming for you and your child. But if you're both prepared, it can be a smooth step on the path to adulthood. Helping Your Teen Find a New Doctor When kids become adults, they can visit an adult primary care physician (PCP), such as an internal medicine doctor (internist), a family medicine doctor, or a general practitioner. Pediatricians are trained to care for newborns to young adults. Not all pediatric practices have the same age limits, so ask your doctor about their policy when your child enters the teen years. Ask your pediatrician for a referral if you don't have a family doctor that your child wants to see or if your child has a chronic condition that will need an adult specialist's care. It may be a challenge to find an adult PCP or specialist if your child has a rare condition, disability, or pediatric-onset condition (one that develops only in childhood). You'll want someone who's comfortable caring for these complex needs. So start searching for doctors early, during the teen years. Ask if your child can see a new specialist for a trial period. Then, follow up with the pediatric specialist to talk about how things went. Allow plenty of time for this process. That way, if there's an issue your child can continue seeing the pediatric specialist until you find an adult provider who is a better fit. Helping Your Teen Choose Health Care Coverage If your child is a dependent under your health care coverage, the Affordable Care Act (ACA) allows your child to be covered until age 26. It doesn't matter if your child is in college, living at home, employed, or even married. They still can be on your policy. If your child is a dependent on your job-based health care plan, coverage will expire on the day your child turns 26. So begin looking for new coverage well before this date. If covered through an ACA Health Insurance Marketplace plan, your child can keep the insurance until December 31 of the year they turn 26. What Options Are Available? Many employers offer group health care coverage as part of their employee benefits package. It lets employees customize a plan that may include dental care, vision care, emergency care, and routine medical care. Long-term disability insurance offers medical benefits for those who are out of work for a long period of time. If offered, it's at an added cost. If insured through an employer, your child will pay: • a monthly fee (premium) • any co-pays and out-of-pocket fees that go to health care providers like doctors or pharmacists What if your adult child is no longer covered under your insurance plan and health coverage is not offered by an employer or spouse's plan? Then, they might be eligible for coverage under COBRA, the Consolidated Omnibus Budget Reconciliation Act. This U.S. mandate requires all health insurance carriers to temporarily extend coverage in a group plan to former dependents for up to 36 months. COBRA does not kick in automatically. Your child must apply for coverage and should do so quickly, as the eligibility period is limited. Premiums will be higher than what your child paid as a dependent on your plan. Your child also can opt for individual health coverage through the Marketplace on HealthCare.gov. Most plans are based on your adult child's income. Many are subsidized to make them more affordable. Special Considerations Insurance companies can't turn down people with a pre-existing condition, or charge them more for coverage. If your child has special health care needs, your insurance plan may have an adult disabled child clause. This lets adult children with disabilities stay on a parent's plan indefinitely. Check to see if your insurance company offers this. Adult children who are disabled may receive coverage through the government's Medicaid program if their incomes fail to cover the cost of medical services, or if they qualify for and/or receive Supplemental Security Income (SSI). Those who are disabled before age 22 also may be eligible for Social Security Disability Insurance (SSDI). These benefits are offered to disabled children whose parents paid into Social Security throughout their careers. Kids whose parents have died, are retired, or get disability benefits themselves may qualify for benefits. After getting SSDI for 24 months, they're also eligible for the U.S. government's Medicare insurance plan. Helping Your Teen Be a Responsible Patient Adult health care is based on patient responsibility. With that comes control. So, your child will make all medical decisions and is entitled to privacy about all medical conditions. You won't get that information unless they choose to share it with you. It's important for young adults to share their medical information with all their health care providers. This includes previous illnesses, operations, medicines, and immunizations. They should also mention any allergic reactions to medicines, and any family history of disease, like cancer or heart disease. Encourage your son or daughter to keep copies of all medical records and an up-to-date list of medicines. And while it's important to see a doctor with a health concern, it's also important to go for regular checkups and screenings. Recommended health screenings are based on your child's personal and family medical history. How Can I Help My Kids Take Charge of Their Health Care? Help your kids start \"co-managing\" their health care during the teen years. Little by little, encourage teens to take an active role. They can schedule appointments and refill prescriptions, for example. This builds self-confidence and shows parents that their kids can take care of themselves. The move to adult health care won't happen overnight. But planning ahead and talking about what to expect will help kids manage their medical care when the time comes. Medically reviewed by: Amy E. Renwick, MDThis link will open in a new window Date reviewed: September 2023 More on this topic for: • Parents • Teens More on this topicFor Parents • Financial Planning for Kids With Disabilities • Getting Teens Involved in Their Health Care • Sickle Cell Disease (Topic Center) • How to Shop for Health Insurance • How to Find Affordable Health Care • 18 Year Well-Child Checkup • 19 Year Well-Child Checkup • 20 Year Well-Child Checkup • Medical Care and Your 13- to 18-Year-Old • Electronic Health Records More on this topicFor Teens • I Think I Have a Mental Health Problem. Who Can I Talk To? • Talking to Your Doctor • Health Insurance: Cracking the Code • Health Insurance Basics • Refilling a Prescription • How to Fill a Prescription • Electronic Health Records • Your Medical Records • How Do I Switch Doctors? • Choosing Your Own Doctor View more Share: • Share to Facebook • Share to Twitter • Share to Pinterest RELATED CATEGORIES • Checkups • Doctor & Hospital Visits"
  },
  "source": {
    "name": "kidshealth",
    "urls": {
      "es": "https://kidshealth.org/es/parents/adult-care.html",
      "en": "https://kidshealth.org/en/parents/adult-care.html"
    }
  },
  "updatedAt": "2026-07-03T15:13:45.738Z"
}