{
  "id": "collarbone-fracture",
  "category": "parents",
  "topic": "firstAidSafety",
  "subtopicId": "emergencias",
  "es": {
    "title": "Fractura de clavícula",
    "description": "También recibe el nombre de: Clavícula rota, clavícula fracturada Descripción general ¿Qué es una fractura de clavícula? La clavícula es el hueso que conecta el esternón con el hombro. Se extiende horizontalmente entre la parte superior del esternón y el omóplato. Se puede palpar la clavícula tocando la zona entre el cuello y el hombro. Una clavícula rota se produce cuando este hueso se fractura. Las cosas más importantes que debe saber • Una clavícula rota es una fractura en el hueso que se encuentra entre el pecho y el hombro. • Puede producirse dolor, hinchazón, hematomas, dificultad para mover el brazo o que la piel sobresalga por encima del hueso. • La mayoría de las fracturas se curan con hielo, analgésicos, un soporte para el brazo como un cabestrillo y ejercicios (según las recomendaciones del médico). • El equipo de protección, el calzado adecuado, una dieta saludable y el ejercicio pueden ayudar a prevenir fracturas. Signos y síntomas ¿Cuáles son los signos y los síntomas de una fractura de la clavícula? Una persona que se fractura la clavícula tal vez tenga lo siguiente: • dolor en la clavícula • dificultad para mover o levantar el brazo o el hombro de ese lado • inflamación, dolor y hematomas a lo largo de la clavícula • piel que sobresale o se \"levanta\" por encima de la rotura Causas y prevención ¿Cómo se producen las fracturas de clavícula? Los niños pueden fracturarse la clavícula al caer con fuerza sobre el hombro o el brazo extendido, o si su hombro golpea contra algo o alguien (por ejemplo, al practicar deportes de contacto como fútbol americano, lucha libre, rugby, lacrosse y hockey). ¿Es posible prevenir las fracturas de clavícula? Como las fracturas de la clavícula ocurren de manera inesperada y repentina, es difícil prevenirlas. Pero para disminuir el riesgo, anime a su hijo a: • Utilizar todo el equipo de protección recomendado y aprender las técnicas adecuadas para el deporte, especialmente al practicar deportes de contacto. • Mantener los huesos fuertes con una dieta equilibrada. Incluya muchas verduras y alimentos ricos en calcio y vitamina D en tu dieta para fortalecerlos. • Hacer ejercicios de fuerza y estiramiento para desarrollar músculos fuertes y flexibles. Unos músculos fuertes y flexibles brindan mayor soporte a los huesos, mantienen a los niños ágiles y reducen el riesgo de caídas fuertes. Un calentamiento adecuado, que incluya estiramientos dinámicos, ayuda a que los músculos rindan al máximo durante el juego. • Contar con calzado adecuado que le quede bien y le brinde buen soporte, apropiado para el deporte que practica. Diagnóstico ¿Cómo se diagnostica una fractura en la clavícula? Para diagnosticar una fractura de clavícula, los profesionales del cuidado de la salud preguntan cómo se produjo la lesión, realizan un examen físico y solicitan radiografías. Tratamiento y cuidado ¿Cómo se trata una fractura de clavícula? La mayoría de las fracturas de clavícula sanan con un cabestrillo y reposo. A veces, los niños pueden usar un inmovilizador de hombro en lugar de un cabestrillo. Un inmovilizador de hombro es similar a un cabestrillo, pero también tiene una correa que se ajusta alrededor de la cintura. El hielo y los analgésicos ayudan a aliviar el dolor y la inflamación durante la recuperación. A medida que su hijo se sienta mejor, su médico podría recomendarle algunos ejercicios o fisioterapia para fortalecerlo. Llame a su médico si su hijo presenta dolor o hinchazón que empeora. Otras preguntas habituales ¿Cuánto tiempo tarda en curarse una clavícula rota? La mayoría de las fracturas de clavícula se curan rápidamente y por completo. En pocos meses, los niños suelen poder retomar todas sus actividades previas a la lesión. ¿La clavícula se soldará derecha? Aunque las clavículas no estén perfectamente alineadas, el cuerpo suele enderezarlas nuevamente. Esto se debe a que la clavícula tiene un periostio grueso (la membrana que recubre el hueso). El periosto de la clavícula no suele fracturarse y, entonces, actúa como una manga que mantiene unido al hueso mientras se cura. En casos excepcionales, si el hueso está muy desalineado, el médico tal vez recomiende una cirugía. En algunos casos, hay un bulto en el lugar de la fractura del hueso. En los niños que aún están creciendo, este bulto suele hacerse más pequeño y desaparecer en un año. A veces, el bulto no desaparece por completo. Pero no causa dolor ni ningún otro problema con el brazo o el hombro. ¿Cuándo puede retomar los deportes mi hijo? El profesional del cuidado de la salud volverá a ver a su hijo y le indicará cuándo puede retomar la práctica deportiva. Esto suele ocurrir cuando: • No sienta dolor cuando el profesional del cuidado de la salud presiona la clavícula. • La fuerza del hombro es normal. • Su hijo puede mover y usar el brazo y el hombro sin dolor. En general, los niños pueden volver a practicar deportes sin contacto (como correr o nadar) en unas seis semanas y deportes de contacto (como fútbol americano, lacrosse y hockey) en 8 a 12 semanas."
  },
  "en": {
    "title": "Broken Collarbone (Clavicle Fracture)",
    "description": "Also called: Broken Clavicle, Fractured Clavicle, Fractured Collarbone Overview What Is a Broken Collarbone? The collarbone (also called the clavicle) is the bone that connects the breastbone to the shoulder. The collarbone runs horizontally between the top of the breastbone (sternum) and shoulder blade (scapula). You can feel the collarbone by touching the area between the neck and the shoulder. A broken collarbone is when this bone breaks. Top Things to Know • A broken collarbone is a break in the bone that runs between the chest and shoulder. • Pain, swelling, bruising, trouble moving the arm, or skin sticking up over the bone can happen. • Most breaks heal with ice, pain medicine, arm support like a sling, and exercise (as the doctor recommends). • Protective gear, supportive shoes, a healthy diet, and exercise may help prevent breaks. Signs & Symptoms What Are the Signs & Symptoms of a Broken Collarbone? Someone who breaks a collarbone might have: • pain over the collarbone • trouble moving or lifting the arm or shoulder on that side • swelling, tenderness, and bruising along the collarbone • skin sticking up or \"tenting\" above the break Causes & Prevention How Do Broken Collarbones Happen? Kids can get a collarbone fracture by falling hard on a shoulder or an outstretched arm, or if their shoulder hits against something or someone (for example, while playing contact sports like football, wrestling, rugby, lacrosse, and hockey). Can Broken Collarbones Be Prevented? Because collarbone fractures happen suddenly and unexpectedly, it can be hard to prevent them. But to decrease the risk, encourage your child to: • Wear all the recommended protective gear and learn the proper techniques for the sport — when playing contact sports. • Keep bones strong by eating a well-balanced diet. Serve lots of vegetables and foods that are rich in calcium and vitamin D to help build strong bones. • Do strength training and stretching to build strong, flexible muscles. Muscles that are strong and flexible will help support bones better and keep kids agile and less likely to experience a hard fall. A proper warm-up, including dynamic stretching exercises, can help muscles perform at their best during play. • Wear well-fitting, supportive footwear that's right for the sport. Diagnosis How Is a Broken Collarbone Diagnosed? To diagnose a collarbone fracture, healthcare providers ask about how the injury happened, do an exam, and order X-rays. Treatment & Care How Is a Broken Collarbone Treated? Most broken collarbones heal with a sling and some rest. Sometimes kids might use a shoulder immobilizer instead of a sling. A shoulder immobilizer is like a sling, but also has a strap that goes around the waist. Ice and pain medicine help with pain and swelling during recovery. As your child starts feeling better, your healthcare provider may recommend some exercises or physical therapy to help improve strength. Call your healthcare provider if your child has pain or swelling that gets worse. Other Common Questions How Long Does It Take for a Broken Collarbone to Heal? Most broken collarbones heal quickly and completely. Within a few months, kids usually can do everything they did before the injury. Will the Collarbone Heal Straight? Even if the broken bones aren't perfectly lined up, the body usually can make them straight again. That's because the collarbone has a thick periosteum (outer liner on the bone). The collarbone periosteum doesn't usually break, so it acts like a sleeve to hold the bone together while it heals. Rarely, the doctor might recommend surgery if the broken bones are very out of line. Sometimes, there's a bump where the bone broke. In kids who are still growing, the bump tends to get smaller and go away within a year. Sometimes the bump doesn't fully go away. But it doesn't hurt or cause other problems with the arm or shoulder. When Can My Child Go Back to Sports? Your healthcare provider will see your child again and let you know when it's OK to go back to sports. This is usually when: • There's no pain when the healthcare provider presses on the collarbone. • Shoulder strength is normal. • Your child can move and use the arm and shoulder without pain. In general, kids can go back to noncontact sports (such as running or swimming) in about six weeks and contact sports (such as football, lacrosse, and hockey) in 8–12 weeks. Medically reviewed by: Melanie L. Pitone, MDThis link will open in a new window Date reviewed: January 2024 More on this topic for: • Parents • Kids • Teens More on this topicFor Parents • Broken Bones • How Long Does it Take for a Broken Bone to Heal? • Broken Bone (Fracture): Treatment & Care • How to Handle Falls • How Broken Bones Heal • Preventing Injuries From Falling, Climbing, and Grabbing • Preventing Children's Sports Injuries More on this topicFor Kids • 5 Ways to Avoid Sports Injuries • Your Bones • Getting an X-ray (Video) • How Does the Skeletal System (Bones) Work? (Video) • Quiz: Bones • Activity: Bones • Casts More on this topicFor Teens • Dealing With Sports Injuries • Sports and Exercise Safety • Bones, Muscles, and Joints • Casts • Stress Fractures • Splints View more Share: • Share to Facebook • Share to Twitter • Share to Pinterest RELATED CATEGORIES • Bones & Muscles • Emergencies"
  },
  "source": {
    "name": "kidshealth",
    "urls": {
      "es": "https://kidshealth.org/es/parents/collarbone-fracture.html",
      "en": "https://kidshealth.org/en/parents/collarbone-fracture.html"
    }
  },
  "updatedAt": "2026-07-03T14:59:42.588Z"
}