{
  "id": "jock-itch-15",
  "category": "teenagers",
  "topic": "infections",
  "subtopicId": "infecciones-cutaneas-y-erupciones",
  "es": {
    "title": "Tiña inguinal",
    "description": "La tiña inguinal es una infección fúngica en el área de la ingle. Los síntomas incluyen picazón, enrojecimiento y descamación. Es común en adolescentes y adultos jóvenes. El tratamiento incluye medicamentos antifúngicos tópicos. La prevención incluye mantener el área seca y limpia."
  },
  "en": {
    "title": "Jock Itch",
    "description": "What Is Jock Itch? Jock itch is a skin infection caused by a fungus. It's called jock itch because it's commonly seen in active people who sweat a lot while playing sports. But anyone can get this infection. What Are the Signs & Symptoms of Jock Itch? Jock itch (or tinea cruris) usually causes redness, flakiness, peeling, or cracking of the skin in the groin, thigh, and buttocks area. The rash can look circular, with well-defined or even elevated edges. It can also spread to the area around the anus (where poop comes out). It may itch, sting, or burn, or simply feel uncomfortable. What Causes Jock Itch? A fungus is a microscopic organism that thrives in damp, warm environments. Fungi usually aren't dangerous. But when they infect the skin, they cause mild but annoying rashes (also known as tinea infections). Jock itch is caused by fungi that normally live on the skin, hair, and nails, called dermatophytes. When the groin, upper thighs, and buttocks area gets warm and moist, they can grow out of control and start to cause symptoms. Is Jock Itch Contagious? Yes. Jock itch can spread from one person to another by skin-to-skin contact, especially in warm, damp environments. It can also spread to other areas of the body if someone touches the affected area and touches other body parts. Jock itch often spreads from a fungal infection on the feet, known as athlete's foot. Who Gets Jock Itch? Jock itch can affect anyone who tends to sweat a lot. It most often affects guys, but girls can get it too. Things that can make jock itch more likely include: • lots of sweating while playing sports • hot and humid weather • friction from wearing tight clothes (like bathing suits) for long periods • sharing clothes or towels with others • not drying the skin well after sweating, bathing, or swimming • some health conditions (such as diabetes, obesity, or immune system problems) How Is Jock Itch Diagnosed? A doctor can often diagnose jock itch just by looking at it and asking about symptoms and a person's lifestyle. Sometimes the doctor will scrape off a small sample of the flaky infected skin to look at under a microscope or to test in a laboratory. How Is Jock Itch Treated? Over-the-counter (OTC) antifungal creams, sprays or powders may solve the problem if it is mild. More serious infections may need prescription medicine, either topical (applied to skin) or in pill form. You should use the medicine as long as is recommended, even if the rash seems to be getting better. If not, the infection can come back. Some people regularly use medicated powders and sprays to prevent this from happening. To help heal the skin, it's important to keep the affected area clean and dry. Be sure to: • Wash and then dry the area with a clean towel. (Use a separate clean towel for the rest of your body.) • Apply the antifungal cream, powder, or spray as directed on the label. • Change clothing, especially underwear, every day. • Treat any other fungal infections, such as athlete's foot. How Long Does Jock Itch Last? Jock itch is usually less severe than other tinea infections. If it's not treated, though, it can last for weeks or months. Can Jock Itch Be Prevented? Jock itch often can be prevented. To avoid it: • Keep the groin area clean and dry. Wash daily and dry off completely, particularly after showering, swimming, and sweaty activities. • Use clean towels and avoid sharing clothing and towels. • Wash athletic supporters (jock straps) as often as possible. • Avoid tight-fitting clothing. • Change clothing, especially underwear, every day. • Treat any other fungal infections, such as athlete's foot. If you have athlete's foot, dry your feet with a separate towel. Then, put socks on before underwear so that fungus from your feet doesn't get on the underwear. Medically reviewed by: Yamini Durani, MDThis link will open in a new window Date reviewed: March 2023 More on this topic for: • Teens More on this topicFor Teens • Vitiligo • Athlete's Foot • Tips for Taking Care of Your Skin • Hygiene Basics • Ringworm: Signs, Causes & Treatment • Hair, Skin, and Nails View more Share: • Share to Facebook • Share to Twitter • Share to Pinterest RELATED CATEGORIES • Fungal Infections • Skin Infections & Rashes • Skin, Hair & Nails • Sports Injuries"
  },
  "source": {
    "name": "kidshealth",
    "urls": {
      "es": "https://kidshealth.org/es/teens/jock-itch.html",
      "en": "https://kidshealth.org/en/teens/jock-itch.html"
    }
  },
  "updatedAt": "2026-07-03T18:10:11.825Z"
}