{
  "id": "meds",
  "category": "teenagers",
  "topic": "body",
  "subtopicId": "obtencion-de-atencion-medica",
  "es": {
    "title": "Medicamentos: qué son y para qué sirven",
    "description": "A veces parece que hay más medicamentos que enfermedades, y esto te puede confundir. En EE.UU., algunos medicamentos se pueden comprar sin receta médica, sea en farmacias, droguerías u otros establecimientos comerciales. Otros medicamentos requieren receta médica para poderlos comprar. Algunos medicamentos que solo se pueden adquirir en hospitales. ¿Qué son los medicamentos? Los medicamentos son compuestos químicos que se utilizan para curar, detener o prevenir enfermedades; para aliviar síntomas; o para ayudar a diagnosticar algunas enfermedades. Los avances en los medicamentos han hecho posible que lo médicos curen muchas enfermedades y salven muchas vidas. En la actualidad, se obtienen medicamentos de una amplia variedad de fuentes. Muchos medicamentos se desarrollaron a partir sustancias de la naturaleza, e, incluso hoy en día, se siguen extrayendo de las plantas. Algunos medicamentos se fabrican en laboratorios, mezclando una serie de sustancias químicas. Otros, como la penicilina, son subproductos fabricados por organismos como los hongos. Y unos pocos de ellos se obtienen a través de la ingeniería biológica, introduciendo genes en bacterias, que se encargan de fabricar la sustancia deseada. Cuando pensamos en tomar medicamentos, solemos pensar en las pastillas. Pero los medicamentos se pueden administrar de muchas formas diferentes, como las siguientes: • líquidos que se tragan • gotas que se colocan en las orejas o los ojos • cremas, geles o pomadas que se aplican sobre la piel • inhaladores (como los espráis nasales o los nebulizadores para el asma) • parches que se pegan sobre la piel (llamados parches transdérmicos) • pastillas que se colocan debajo de la lengua (llamadas sublinguales; se absorben a través de los vasos sanguíneos y entran en el torrente sanguíneo) • inyecciones y medicamentos intravenosos (estos últimos se insertan dentro de una vena) En EE.UU., no se puede comercializar ningún medicamento que no haya sido aprobado por la Administración de Alimentos y Medicamentos (FDA, por sus siglas en inglés). La industria farmacéutica hace las pruebas necesarias en todos los medicamentos nuevos y envía sus resultados a la FDA. La FDA solo permite el uso de medicamentos nuevos que sean eficaces y lo bastante seguros. Cuando las ventajas de utilizar un medicamento superan sus riesgos, la FDA suele aprobar su comercialización. La FDA puede retirar un medicamento del mercado en cualquier momento, si se constata que provoca efectos secundarios nocivos. page 1 Distintos tipos de medicamentos Los medicamentos actúan de formas diferentes. Algunos pueden curar enfermedades matando o deteniendo el avance de los gérmenes invasores, como las bacterias y los virus. Otros se utilizan para tratar el cáncer, matado las células mientras se dividen o impidiendo que se sigan multiplicando. Algunos medicamentos se limitan a aportar sustancias que faltan o a corregir unas concentraciones excesivamente bajas de sustancias químicas naturales del cuerpo, como las hormonas o las vitaminas. Y hay medicamentos que hasta pueden afectar a partes del sistema nervioso que controlan procesos del cuerpo. Casi todo el mundo ha tomado antibióticos alguna vez. Los antibióticos son un tipo de medicamento que lucha contra las infecciones bacterianas. Tu médico te puede recetar antibióticos para afecciones como la faringitis estreptocócica o las infecciones de oído. Los antibióticos funcionan matando las bacterias o bien impidiendo que se multipliquen para que el sistema inmunitario pueda combatir la infección. A veces, una parte del cuerpo no puede fabricar una cantidad suficiente de una sustancia química. Y eso te puede hacer enfermar. Por ejemplo, una persona con una diabetes dependiente de la insulina tiene un páncreas que no puede fabricar una cantidad suficiente de insulina (una hormona que regula las concentraciones de glucosa en sangre). También hay gente que produce muy poca cantidad de la hormona tiroidea, que ayuda al cuerpo a utilizar la energía. En ambos casos, los médicos pueden recetar medicamentos para compensar esas deficiencias hormonales. Algunos medicamentos tratan los síntomas, pero no pueden curar la enfermedad que los provoca. (Un síntoma es lo que sientes cuando estás enfermo, como la tos o las náuseas.) Por lo tanto, el hecho de tomar pastillas para la garganta te puede aliviar el dolor de garganta, pero no matará los molestos estreptococos que la han invadido. Algunos medicamentos alivian el dolor. Si te haces una distensión muscular, es posible que tu médico te diga que tomes ibuprofeno o paracetamol. Estos medicamentos para aliviar el dolor, conocidos como analgésicos, no te eliminarán el origen del dolor y tu músculo seguirá estando distendido. Lo que harán es bloquear las vías nerviosas encargadas de trasmitir las señales de dolor desde la parte del cuerpo lesionada o irritada hasta el cerebro (en otras palabras, afectan a la forma en que el cerebro lee las señales de dolor) para que no te duela tanto mientras tu cuerpo se vaya recuperando. Cuando la gente envejece, a veces desarrolla afecciones crónicas o de larga duración. Los medicamentos pueden ayudar a controlar algunas de estas afecciones, como la hipertensión arterial (tensión arterial alta) o el colesterol alto. Estos medicamentos no permiten curar la causa subyacente del problema, pero pueden ayudar a prevenir algunos de sus efectos nocivos sobre el cuerpo a lo largo del tiempo. Entre los medicamentos más importantes, se encuentran las vacunas. Las vacunas impiden que la gente enferme en primer lugar, al inmunizarla, protegiendo a su cuerpo de algunas enfermedades infecciosas. Las vacunas suelen contener una cantidad reducida de un agente similar a un germen o gérmenes específicos que han sido modificados o matados previamente. Cuando se vacuna a una persona, se prepara al sistema inmunitario a \"recordar\" el germen para que pueda combatir este tipo de infección en el futuro. La mayoría de las vacunas que permiten prevenir enfermedades como el sarampión, la tos ferina y la varicela, se administran en forma de inyección. A nadie le gusta que le pongan inyecciones. Pero las enfermedades que previenen pueden ser muy graves y causar síntomas que duran mucho más que la molestia puntual de un pinchazo. Para hacer la vida más fácil, ahora te puedes vacunar en las farmacias. Aunque algunos medicamentos requieren receta médica, hay otros que se pueden comprar sin receta, en droguerías u otros establecimientos comerciales. Puedes comprar medicamentos contra el dolor, contra la fiebre, para la tos y para la alergia sin receta médica. Pero el hecho de que un medicamento se pueda adquirir sin receta médica no implica que no tenga efectos secundarios. Este tipo de medicamentos se deben administrar con las mismas precauciones que los que se venden con receta médica. page 2 La toma de medicamentos Independientemente del tipo de medicamento que te receten, siempre es importante actuar de una forma segura y seguir algunas normas básicas: • Si te encuentras peor después de tomar un medicamento, informa a tu médico de inmediato. • Comprueba por doble partida que dispones del medicamento adecuado. Si compras el mismo medicamento varias veces, comprueba que se trata del mismo medicamento todas las veces, fijándote en su nombre, su forma, su color y su tamaño. Si dudas al respecto, asegúrate de preguntárselo al farmacéutico. • Lee bien el prospecto y sigue sus indicaciones. Pregunta, si tienes alguna duda. • Toma el medicamento exactamente como te lo hayan recetado. Si las instrucciones te indican que tomes una pastilla cuatro veces al día, no te tomes dos pastillas dos veces al día. No es lo mismo. • Pregunta si el medicamento tiende a afectar las tareas cotidianas, como la conducción de vehículos o la concentración en los estudios. • No tomes más cantidad del medicamento de la que te hayan recetado. No te hará curarte ni encontrarte mejor más deprisa. De hecho, una sobredosis de muchos medicamentos puede hacer que te encuentres muy mal. • Sigue siempre las instrucciones que te dé tu médico o farmacéutico. Por ejemplo, es posible que te diga que te tomes el medicamento con alimentos para reducir el malestar estomacal que te podría provocar, o bien que te lo tomes con el estómago vacío para que los alimentos no interfieran en la absorción del medicamento por parte del cuerpo. • No compartas nunca un medicamento que te hayan recetado a ti con otra persona, incluso aunque creas que a la otra persona le pasa lo mismo que a ti. Los medicamentos actuales son muy complicados y sus dosis se deben rectar específicamente para cada persona, teniendo en cuenta sus necesidades. Tomar dosis más bajas o más altas de lo necesario puede ser nocivo. Además, el cuerpo de otra persona puede reaccionar de forma diferente a un medicamento que te han recetado a ti (por ejemplo, si la persona es alérgica a uno de los componentes del medicamento). • Si ya te estás medicando, pero quieres tomar otro medicamento de venta sin receta médica, pregúntaselo antes al farmacéutico. Podría haber interacciones entre medicamentos. • Informa siempre a tu médico o farmacéutico si estás tomando otro medicamento o suplemento elaborado con plantas medicinales para saber si podría haber alguna interacción entre sus componentes. • Asegúrate de informar a tu médico si estás o podrías estar embarazada. Algunos medicamentos pueden ser nocivos para el bebé. Además, dile al médico o al farmaceuta si estás amamantando a tu bebé ya que algunos medicamentos pueden provocar problemas en el amamantamiento. • Recuerda que el hecho de beber alcohol puede empeorar de forma considerable los efectos secundarios de muchos medicamentos. • Aunque te vuelvas a encontrar mal por algo que crees que es lo mismo que lo que te ocurrió en otra ocasión, no decidas por ti mismo qué es lo que te pasa ni tomes los restos de un medicamento antiguo. Si tomas ese medicamento para una enfermedad distinta, lo más probable es que no funcione y, además, podría ser peligroso para tu salud. Habla antes con tu médico. • Cuando te receten antibióticos, tómalos durante el ciclo completo de tratamiento, incluso aunque empieces a encontrarte mejor; así eliminarás a todos los gérmenes y la infección no se reactivará. • De ser posible, conserva el medicamento en su envase original. • No utilices medicamentos caducados, sobre todo si se trata de medicamentos de venta con receta médica. • Los medicamentos no se deben guardar en el baño porque el calor y la humedad pueden repercutir en su eficacia. La mayoría de los medicamentos se deben guardar en lugares secos, a temperatura ambiente y alejados de la luz solar. Algunos de ellos se deben guardar en la nevera. Si no estás seguro, pregúntaselo a tu médico o farmacéutico. • Asegúrate de guardar todos tus medicamentos en un lugar seguro, fuera del alcance de tus hermanos pequeños y de tus mascotas. • Si tienes alguna alergia, asegúrate de informar a tu médico o farmacéutico antes de empezar a tomar un medicamento nuevo. • Si te sale una erupción en la piel, tienes picores o problemas para respirar después de empezar a tomar un medicamento nuevo, díselo a tus padres de inmediato. Tener dificultades para respirar, desarrollar ampollas por el cuerpo y/o tener una repentina inflamación en la lengua, los labios, la cara u otras partes del cuerpo pueden ser signos de una reacción alérgica grave: pide ayuda médica urgente de inmediato. A veces, tener que tomar medicamentos puede ser un fastidio. Pero los medicamentos son los tratamientos más eficaces de muchas enfermedades. Si alguna vez tienes dudas o preguntas sobre cómo actúa un medicamento o sobre cómo lo deberías tomar, habla con tu médico o farmacéutico al respecto."
  },
  "en": {
    "title": "Understanding Medicines and What They Do",
    "description": "Sometimes it seems like there are more medicines than there are diseases, and it can be hard to keep them straight. Some can be bought over the counter at pharmacies or other stores. Others require a doctor's prescription. Some are available only in hospitals. What Are Medicines? Medicines are chemicals or compounds used to cure, halt, or prevent disease; ease symptoms; or help in the diagnosis of illnesses. Advances in medicines have enabled doctors to cure many diseases and save lives. These days, medicines come from a variety of sources. Many were developed from substances found in nature, and even today many are extracted from plants. Some medicines are made in labs by mixing together a number of chemicals. Others, like penicillin, are byproducts of organisms such as fungus. And a few are even biologically engineered by inserting genes into bacteria that make them produce the desired substance. When we think about taking medicines, we often think of pills. But medicines can be delivered in many ways, such as: • liquids that are swallowed • drops that are put into ears or eyes • creams, gels, or ointments that are rubbed onto the skin • inhalers (like nasal sprays or asthma inhalers) • patches that are stuck to skin (called transdermal patches) • tablets that are placed under the tongue (called sublingual medicines; the medicine is absorbed into blood vessels and enters the bloodstream) • injections (shots) or intravenous (inserted into a vein) medicines No medicine can be sold unless it has first been approved by the U.S. Food and Drug Administration (FDA). The makers of the medicine do tests on all new medicines and send the results to the FDA. The FDA allows new medicines to be used only if they work and if they are safe enough. When a medicine's benefits outweigh its known risks, the FDA usually approves the sale of the drug. The FDA can withdraw a medicine from the market at any time if it later is found to cause harmful side effects. page 1 Different Types of Medicines Medicines act in a variety of ways. Some can cure an illness by killing or halting the spread of invading germs, such as bacteria and viruses. Others are used to treat cancer by killing cells as they divide or preventing them from multiplying. Some drugs replace missing substances or correct low levels of natural body chemicals such as some hormones or vitamins. Medicines can even affect parts of the nervous system that control a body process. Nearly everyone has taken an antibiotic. This type of medicine fights bacterial infections. Your doctor may prescribe an antibiotic for things like strep throat or an ear infection. Antibiotics work either by killing bacteria or halting their multiplication so that the body's immune system can fight off the infection. Sometimes a part of the body can't make enough of a chemical. That can also make you sick. Someone with insulin-dependent diabetes, for instance, has a pancreas that can't produce enough insulin(a hormone that regulates glucose in the body). Some people have a low production of thyroid hormone, which helps control how the body uses energy. In each case, doctors can prescribe medicines to replace the missing hormone. Some medicines treat symptoms but can't cure the illness that causes the symptoms. (A symptom is anything you feel while you're sick, such as a cough or nausea.) So taking a lozenge may soothe a sore throat, but it won't kill that nasty strep bacteria. Some medicines relieve pain. If you pull a muscle, your doctor might tell you to take ibuprofen or acetaminophen. These pain relievers, or analgesics, don't get rid of the source of the pain — your muscle will still be pulled. What they do is block the pathways that transmit pain signals from the injured or irritated body part to the brain (in other words, they affect the way the brain reads the pain signal) so that you don't hurt as much while your body recovers. As people get older, they sometimes develop chronic or long-term conditions. Medicines can help control things like high blood pressure (hypertension) or high cholesterol. These drugs don't cure the underlying problem, but they can help prevent some of its body-damaging effects over time. Among the most important medicines are immunizations (or vaccines). These keep people from getting sick in the first place by immunizing, or protecting, the body against some infectious diseases. Vaccines usually contain a small amount of an agent that resembles a specific germ or germs that have been modified or killed. When someone is vaccinated, it primes the body's immune system to \"remember\" the germ so it will be able to fight off infection by that germ in the future. Most immunizations that prevent you from catching diseases like measles, whooping cough, and chickenpox are given by injection. No one thinks shots are fun. But the diseases they prevent can be very serious and cause symptoms that last much longer than the temporary discomfort of the shot. To make life easier, now you can get immunizations at many pharmacies. Although some medicines require a prescription, some are available in stores. You can buy many medicines for pain, fever, cough, or allergies without a prescription. But just because a medicine is available over-the-counter (OTC), that doesn't mean it's free of side effects. Take OTC medicines with the same caution as those prescribed by a doctor. page 2 Taking Medicines No matter what type of medicine your doctor prescribes, it's always important to be safe and follow some basic rules: • If you feel worse after taking a medicine, tell your doctor right away. • Double-check that you have the right medicine. If you get the same prescription filled more than once, check that it's the same shape, size, and color as the last time. If not, be sure to ask the pharmacist about it. • Read the label and follow directions. Ask if you have questions. • Take medicines exactly as prescribed. If the instructions say take one tablet four times a day, don't take two tablets twice a day. It's not the same. • Ask if the medicine is likely to affect everyday tasks such as driving or concentrating in school. • Don't take more medicine than is recommended. It won't make you heal faster or feel better quicker. In fact, an overdose of medicine can make you sick. • Always follow your doctor's or pharmacist's instructions. For instance, he or she may tell you to take a medicine with food to help lessen the stomach upset it can cause or instead to take the medicine on an empty stomach so as not to interfere with the medicine's absorption into your body. • Never share prescription medicine with anyone else, even if that person has the same thing as you do. Today's medicines are very complex, and the dosages tend to be precisely prescribed for each person's needs. Either under-dosing or overdosing can be harmful. Additionally, someone else's body may react differently to the same medicine (for example, if the person has an allergy to one of the components of the medicine). • If you're already taking a medicine but also want to take something you can buy over-the-counter, ask the pharmacist. There could be a bad interaction between the medicines. • Always tell your doctor and pharmacist if you're taking any other medicines or any herbal supplements so that he or she can check for any interactions between the medicines. • Be sure to tell your doctor if you are pregnant or might be pregnant. Some medicines can be harmful to the baby. Also, let your doctor or pharmacist know if you are breastfeeding, as some medications can cause problems with nursing. • Remember that drinking alcohol can dramatically worsen the side effects of many medicines. • Even if you get sick with what you think is the same old thing, don't decide on your own that you know what's wrong and take some leftover medicine. Taking that medicine for a different disease might not work — and it can even be harmful. Talk to your doctor first. • Take antibiotics for the full length of the time prescribed, even if you start to be feel better, so that all the germs are killed and the infection doesn't bounce back. • Keep medicines in their original labeled containers, if possible. • Don't use medicine that has expired, especially prescription medicine. • Medicines should not be stored in your bathroom because heat and humidity can affect the potency of the drug. Most medicines should be kept at room temperature and away from sunlight. Some must be refrigerated. Check with your pharmacist or doctor if you aren't sure. • Make sure all medicines are stored safely and out of the reach of younger brothers or sisters and pets. • If you have any allergies, tell your doctor and pharmacist before they start you on a new medicine. • If you get a rash, start itching, vomiting, or have trouble breathing after starting a medicine, tell your parents immediately. Breathing difficulty, breaking out in hives, or suddenly developing swelling of the tongue, lips, face, or other body parts may be signs of a severe allergic reaction — get emergency medical care right away. Taking medicines may feel like a hassle sometimes. But medicines are the most effective treatments available for many illnesses. If you ever have any questions about what a medicine does or how you should take it, talk with your doctor or a pharmacist. Medically reviewed by: Elora Hilmas, PharmD, BCPSThis link will open in a new window Date reviewed: October 2018 More on this topic for: • Teens More on this topicFor Teens • ADHD Medicines • Medicines for Diabetes • Taking Prescription Opioid Pain Medicines Safely • Prescription Drug Abuse • Refilling a Prescription • How to Fill a Prescription • 5 Tips for Dealing With Shots • Vaccine Basics • Getting Rid of Old Medicines • Sports Supplements View more Share: • Share to Facebook • Share to Twitter • Share to Pinterest RELATED CATEGORIES • Medical Care • Medications & Treatments"
  },
  "source": {
    "name": "kidshealth",
    "urls": {
      "es": "https://kidshealth.org/es/teens/meds.html",
      "en": "https://kidshealth.org/en/teens/meds.html"
    }
  },
  "updatedAt": "2026-07-03T17:34:48.527Z"
}