{
  "id": "premature-ventricular-contractions",
  "category": "parents",
  "topic": "diseasesConditions",
  "subtopicId": "corazon-y-vasos-sanguineos",
  "es": {
    "title": "Contracciones ventriculares prematuras",
    "description": "¿Qué es una contracción ventricular prematura? Una contracción ventricular prematura es un latido precoz que ocurre entre dos latidos normales. La mayoría de las contracciones ventriculares prematuras son inofensivas. ¿Cómo ocurren las contracciones ventriculares prematuras? El nodo sinusal actúa como el marcapasos del corazón. Esta agrupación de células genera impulsos eléctricos que controlan el ritmo cardíaco. Se encuentra dentro de la aurícula derecha, en la parte superior del corazón. Las contracciones ventriculares prematuras ocurren cuando un latido precoz empieza en uno de los ventrículos, las dos cavidades inferiores del corazón. ¿Cuáles son los signos y los síntomas de las contracciones ventriculares prematuras? La mayoría de las contracciones ventriculares prematuras no provocan síntomas. A veces, se pueden sentir palpitaciones o como si el corazón se salteara un latido. Algunos niños con contracciones ventriculares prematuras se marean y sienten como si se fueran a desmayar. ¿Cuáles son las causas de las contracciones ventriculares prematuras? Los médicos no están seguros de cuáles son las causas de las contracciones ventriculares prematuras. Algunas de las cosas que las pueden desencadenar son las siguientes: • los medicamentos • el alcohol • la cafeína • la nicotina • la ansiedad ¿Cómo se diagnostican las contracciones ventriculares prematuras? Para diagnosticar una contracción ventricular prematura, los médicos auscultan al niño para oírle el corazón, evalúan su estado de salud y le mandan algunas pruebas. Muchas de estas pruebas estudian las señales eléctricas del corazón mientras late para saber cómo está funcionando. Las pruebas que se hacen para estudiar las contracciones ventriculares prematuras son indoloras. Entre ellas, se encuentran las siguientes: • Electrocardiograma (ECG o EKG): viene a ser una fotografía de la actividad eléctrica del corazón. • Ecocardiograma: esta ecografía estudia el tamaño y la estructura interna del corazón. • Holter: un pequeño dispositivo registra las señales eléctricas del corazón mientras un niño lo lleva puesto. Según el tipo de monitor, se debe llevar puesto uno o más días. • Prueba de esfuerzo: una máquina registra las señales eléctricas del corazón mientras el niño hace ejercicio físico. ¿Cómo se tratan las contracciones ventriculares prematuras? La mayoría de los niños con contracciones ventriculares prematuras tienen el corazón sano y no requieren ningún tipo de atención especial. Si su hijo tiene problemas cardíacos o tiene contracciones ventriculares prematuras con frecuencia, su cardiólogo le puede recetar un medicamento para que este tipo de contracciones ventriculares ocurran con menor frecuencia. A una cantidad reducida de niños que tienen una enfermedad cardíaca y contracciones ventriculares prematuras, les puede ayudar un procedimiento cardíaco llamado ablación. La ablación destruye o deja una cicatriz en una pequeña área de tejido donde se inicia el latido precoz. ¿Es posible prevenir las contracciones ventriculares prematuras? Las contracciones ventriculares prematuras no se pueden prevenir, pero usted y su hijo pueden hacer algunas cosas para que no empeoren: • Convierta su casa y su coche en áreas libres de humo, y pida a los demás que no fumen cerca de su hijo. Si en su casa hay alguien que fuma, llame al 1-800-QUIT-NOW en busca de ayuda para abandonar ese hábito. • Los adolescentes no deben beber alcohol ni usar drogas ilegales. • Algunos niños desarrollan contracciones ventriculares prematuras debido al consumo de cafeína. La cafeína se encuentra en bebidas como el café, el té, la cola y las bebidas energizantes. Si su hijo consume estas bebidas, dígale que se cambie a las bebidas descafeinadas. • Pregúntele al cardiólogo si su hijo debe evitar algunos medicamentos o plantas medicinales."
  },
  "en": {
    "title": "Premature Ventricular Contractions",
    "description": "What Is a Premature Ventricular Contraction? A premature ventricular contraction (PVC) is an early heartbeat that happens between normal heartbeats. Most PVCs are harmless. How Does a Premature Ventricular Contraction Happen? The sinus node acts as the heart's pacemaker. This cluster of cells generates the electrical impulses that control the heart's rhythm. It's in the right atrium, in the upper right side of the heart. A PVC happens when an early heartbeat starts in one of the ventricles, the heart's two lower chambers. What Are the Signs & Symptoms of Premature Ventricular Contractions? Most PVCs don't cause symptoms. Sometimes they can feel like a skipped or pounding heartbeat. Some kids who have a lot of PVCs get dizzy and may feel like they're going to faint. What Causes Premature Ventricular Contractions? Doctors aren't sure what causes PVCs. Some things that may trigger them are: • medicines • alcohol • caffeine • nicotine • anxiety How Are PVCs Diagnosed? To diagnose a PVC, doctors listen to the heart, check the child's health, and do some tests. Many PVC tests look at the heart's electrical signals as it beats to \"see\" the heart working. Tests for kids with PVCs are painless. They include: • Electrocardiogram (ECG or EKG): This takes a snapshot of the heart's electrical activity. • Echocardiogram: This ultrasound looks at the size and make-up of the inside of the heart. • Holter monitor: This small device records the heart's electric signals while a child wears it. Depending on the type of monitor, it may be worn for one or more days. • Exercise testing: A machine records the heart's electric signals while the child exercises. How Are Premature Ventricular Contractions Treated? Most kids with PVCs have healthy hearts and do not need special care. If your child has heart problems or gets PVCs often, your cardiologist may prescribe medicine to make them happen less often. For a few kids who have heart disease and PVCs, a heart procedure called an ablation can help. Ablation (a-BLAY-shen) destroys or scars a tiny area of tissue where the early heartbeat starts. Can Premature Ventricular Contractions Be Prevented? PVCs can't be prevented, but you and your child can do some things so they don't get worse: • Make your home and car smoke-free, and ask others not to smoke near your child. If anyone in your household smokes, call 1-800-QUIT-NOW for help quitting. • Teens should not drink alcohol or use street drugs. • Some kids get PVCs from caffeine. Caffeine is in drinks like coffee, tea, cola, and energy drinks. If your child drinks these, suggest changing to non-caffeinated drinks. • Ask your cardiologist if your child should avoid any medicines or herbs. Medically reviewed by: Renelle George, MDThis link will open in a new window Date reviewed: March 2024 More on this topic for: • Parents • Kids • Teens More on this topicFor Parents • Heart Health (Topic Center) • Heart Murmurs • Heart and Circulatory System • Congenital Heart Defects • Arrhythmia (Abnormal Heartbeat) • Body Basics: The Heart (Slideshow) More on this topicFor Kids • Heart Murmurs • Your Heart & Circulatory System More on this topicFor Teens • Your Heart & Circulatory System View more Share: • Share to Facebook • Share to Twitter • Share to Pinterest RELATED CATEGORY • Heart & Blood Vessels"
  },
  "source": {
    "name": "kidshealth",
    "urls": {
      "es": "https://kidshealth.org/es/parents/premature-ventricular-contractions.html",
      "en": "https://kidshealth.org/en/parents/premature-ventricular-contractions.html"
    }
  },
  "updatedAt": "2026-07-03T14:38:21.906Z"
}